Workbook

Sheet Assumptions
A1: MODEL ASSUMPTIONS
A2: Blue cells = input assumptions | C2: Source: Assumptions From Haryana rental market, 2025
A3: PROPERTY 1 — Sector 15 Apartment, Faridabad (2 units)
A4: Monthly rent per unit (₹) | B4: 21000 | C4: 2BHK, mid-range residential
A5: Number of units | B5: 2 | C5: Both currently occupied
A6: Annual rent escalation (%) | B6: 0.05
A7: Annual property tax (₹) | B7: 24000 | C7: Faridabad municipal rate est.
A8: Annual maintenance & repairs (₹) | B8: 36000 | C8: ~₹1,500/unit/month avg
A9: Caretaker salary (annual ₹) | B9: 60000 | C9: Shared across S15 & NIT5
A10: Vacancy allowance (%) | B10: 0.05 | C10: 1 month vacant per unit per 2 yrs
A12: PROPERTY 2 — DLF Phase 2 Villa, Gurugram (1 unit)
A13: Monthly rent (₹) | B13: 55000 | C13: 4BHK premium villa
A14: Annual rent escalation (%) | B14: 0.05 | C14: Standard 5% clause
A15: Annual property tax (₹) | B15: 48000 | C15: Gurugram premium zone
A16: Annual maintenance & repairs (₹) | B16: 60000 | C16: Higher upkeep for villa
A17: Property manager fee (annual ₹) | B17: 66000 | C17: ₹5,500/month — 10% of rent
A18: Vacancy allowance (%) | B18: 0.04 | C18: Premium units re-let faster
A20: PROPERTY 3 — NIT 5 Commercial, Faridabad (2 shops)
A21: Monthly rent per shop (₹) | B21: 14000 | C21: Ground-floor commercial
A22: Number of units | B22: 2 | C22: 1 currently occupied, 1 vacant
A23: Annual rent escalation (%) | B23: 0.06 | C23: Commercial escalation higher
A24: Annual property tax (₹) | B24: 18000 | C24: Commercial rate
A25: Annual maintenance (₹) | B25: 24000 | C25: Lower for commercial shell
A26: Caretaker salary (annual ₹) | B26: 60000 | C26: Shared with Sector 15
A27: Vacancy allowance (%) | B27: 0.2 | C27: 1 unit vacant — conservative
A29: PROPERTY 4 — Sushant Lok Studio, Gurugram (1 unit)
A30: Monthly rent (₹) | B30: 18000 | C30: Studio; currently vacant, re-letting Q2
A31: Annual rent escalation (%) | B31: 0.05 | C31: Standard
A32: Annual property tax (₹) | B32: 12000 | C32: Small unit, lower rate
A33: Refurbishment cost (₹, one-off) | B33: 60000 | C33: Paint, fixtures, deep clean
A34: Maintenance (post-refurb annual ₹) | B34: 18000 | C34: Lower ongoing maintenance
A35: Vacancy allowance (%) | B35: 0.33 | C35: ~4 months vacant in Year 1
A37: FINANCIAL ASSUMPTIONS
A38: Discount rate for DCF / IRR (%) | B38: 0.1 | C38: Cost of equity / opportunity cost
A39: Projection horizon (years) | B39: 5 | C39: For DCF calculation
A40: Initial portfolio purchase cost (₹) | B40: 22000000 | C40: Illustrative total invested capital
A41: Terminal cap rate (%) | B41: 0.055 | C41: Used for terminal value calc

Sheet Annual P&L
A1: ANNUAL REVENUE, COSTS TABLE & NET CASH FLOW
A2: Property / Line Item | B2: 2020 | C2: 2021 | D2: 2022 | E2: 2023 | F2: 2024 | G2: 5-Yr Total
A3: GROSS RENTAL INCOME (before vacancies)
A4: Sector 15 Apartment | B4: 504000 | C4: 529200 | D4: 555660 | E4: 583443 | F4: 612615 | G4: =SUM(B4:F4) -> 2784918
A5: DLF Phase 2 Villa | B5: 660000 | C5: 693000 | D5: 727650 | E5: 764032 | F5: 802234 | G5: =SUM(B5:F5) -> 3646916
A6: NIT 5 Commercial | B6: 168000 | C6: 352800 | D6: 370440 | E6: 388962 | F6: 408410 | G6: =SUM(B6:F6) -> 1688612
A7: Sushant Lok Studio | B7: 144000 | C7: 226800 | D7: 238140 | E7: 250047 | F7: 262549 | G7: =SUM(B7:F7) -> 1121536
A8: TOTAL GROSS INCOME | B8: =SUM(B4:B7) -> 1476000 | C8: =SUM(C4:C7) -> 1801800 | D8: =SUM(D4:D7) -> 1891890 | E8: =SUM(E4:E7) -> 1986484 | F8: =SUM(F4:F7) -> 2085808 | G8: =SUM(B8:F8) -> 9241982
A9: VACANCY DEDUCTIONS (lost rent)
A10: Sector 15 — vacancy loss | B10: -25200 | C10: -26460 | D10: -27783 | E10: -29172 | F10: -30631 | G10: =SUM(B10:F10) -> -139246
A11: DLF Villa — vacancy loss | B11: -26400 | C11: -27720 | D11: -29106 | E11: -30561 | F11: -32089 | G11: =SUM(B11:F11) -> -145876
A12: NIT 5 — vacancy loss | B12: -33600 | C12: -28224 | D12: -29635 | E12: -31117 | F12: -32673 | G12: =SUM(B12:F12) -> -155249
A13: Sushant Studio — vacancy loss | B13: 0 | C13: 0 | D13: -9526 | E13: -10002 | F13: -10502 | G13: =SUM(B13:F13) -> -30030
A14: TOTAL VACANCY DEDUCTIONS | B14: =SUM(B10:B13) -> -85200 | C14: =SUM(C10:C13) -> -82404 | D14: =SUM(D10:D13) -> -96050 | E14: =SUM(E10:E13) -> -100852 | F14: =SUM(F10:F13) -> -105895 | G14: =SUM(B14:F14) -> -470401
A15: NET RENTAL INCOME | B15: =B8+B14 -> 1390800 | C15: =C8+C14 -> 1719396 | D15: =D8+D14 -> 1795840 | E15: =E8+E14 -> 1885632 | F15: =F8+F14 -> 1979913 | G15: =SUM(B15:F15) -> 8771581
A17: OPERATING EXPENSES
A18: Property tax — Sector 15 | B18: -24000 | C18: -25200 | D18: -26460 | E18: -27783 | F18: -29172 | G18: =SUM(B18:F18) -> -132615
A19: Property tax — DLF Villa | B19: -48000 | C19: -50400 | D19: -52920 | E19: -55566 | F19: -58344 | G19: =SUM(B19:F19) -> -265230
A20: Property tax — NIT 5 | B20: -18000 | C20: -18900 | D20: -19845 | E20: -20837 | F20: -21879 | G20: =SUM(B20:F20) -> -99461
A21: Property tax — Sushant Studio | B21: -12000 | C21: -12600 | D21: -13230 | E21: -13892 | F21: -14586 | G21: =SUM(B21:F21) -> -66308
A22: Maintenance & repairs — Sector 15 | B22: -36000 | C22: -38000 | D22: -40000 | E22: -42000 | F22: -44000 | G22: =SUM(B22:F22) -> -200000
A23: Maintenance & repairs — DLF Villa | B23: -60000 | C23: -63000 | D23: -66000 | E23: -70000 | F23: -74000 | G23: =SUM(B23:F23) -> -333000
A24: Maintenance & repairs — NIT 5 | B24: -24000 | C24: -25000 | D24: -26000 | E24: -27000 | F24: -28000 | G24: =SUM(B24:F24) -> -130000
A25: Maintenance & repairs — Studio | B25: -60000 | C25: -18000 | D25: -19000 | E25: -20000 | F25: -21000 | G25: =SUM(B25:F25) -> -138000
A26: Caretaker salary (S15 + NIT5) | B26: -120000 | C26: -126000 | D26: -132300 | E26: -138915 | F26: -145861 | G26: =SUM(B26:F26) -> -663076
A27: Property manager fee — DLF Villa | B27: -66000 | C27: -69300 | D27: -72765 | E27: -76403 | F27: -80223 | G27: =SUM(B27:F27) -> -364691
A28: TOTAL OPERATING EXPENSES | B28: =SUM(B18:B27) -> -468000 | C28: =SUM(C18:C27) -> -446400 | D28: =SUM(D18:D27) -> -468520 | E28: =SUM(E18:E27) -> -492396 | F28: =SUM(F18:F27) -> -517065 | G28: =SUM(B28:F28) -> -2392381
A30: NET CASH FLOW (After all costs) | B30: =B15+B28 -> 922800 | C30: =C15+C28 -> 1272996 | D30: =D15+D28 -> 1327320 | E30: =E15+E28 -> 1393236 | F30: =F15+F28 -> 1462848 | G30: =SUM(B30:F30) -> 6379200
A31: Cumulative cash flow | B31: =B30 -> 922800 | C31: =B31+C30 -> 2195796 | D31: =C31+D30 -> 3523116 | E31: =D31+E30 -> 4916352 | F31: =E31+F30 -> 6379200
A33: Portfolio yield % (NCF ÷ ₹2.2Cr invested) | B33: =B30/22000000 -> 0.041945455 | C33: =C30/22000000 -> 0.057863455 | D33: =D30/22000000 -> 0.060332727 | E33: =E30/22000000 -> 0.063328909 | F33: =F30/22000000 -> 0.066493091

Sheet DCF & IRR
A1: DCF VALUATION & IRR ANALYSIS
A2: Discount rate (r) | B2: 0.1
A3: Initial investment (₹) | B3: -22000000
A4: Terminal cap rate (%) | B4: 0.055
A6: Item | B6: 2020 | C6: 2021 | D6: 2022 | E6: 2023 | F6: 2024 | G6: Terminal Value | H6: IRR / NPV
A7: Net cash flow (from P&L) | B7: ='Annual P&L'!B30 -> 922800 | C7: ='Annual P&L'!C30 -> 1272996 | D7: ='Annual P&L'!D30 -> 1327320 | E7: ='Annual P&L'!E30 -> 1393236 | F7: ='Annual P&L'!F30 -> 1462848
A8: Terminal value (Year 5 NCF ÷ cap rate) | G8: =F7/B4 -> 26597236
A9: Total cash flow incl. terminal (Year 5) | B9: =B7 -> 922800 | C9: =C7 -> 1272996 | D9: =D7 -> 1327320 | E9: =E7 -> 1393236 | F9: =F7+G8 -> 28060084
A10: Discount factor 1/(1+r)^n | B10: =1/(1+$B$2)^1 -> 0.90909091 | C10: =1/(1+$B$2)^2 -> 0.82644628 | D10: =1/(1+$B$2)^3 -> 0.7513148 | E10: =1/(1+$B$2)^4 -> 0.68301346 | F10: =1/(1+$B$2)^5 -> 0.62092132
A11: Present value of cash flows | B11: =B9*B10 -> 838909.09 | C11: =C9*C10 -> 1052062.8 | D11: =D9*D10 -> 997235.16 | E11: =E9*E10 -> 951598.93 | F11: =F9*F10 -> 17423105
A13: Sum of PV (cash flows + terminal) | B13: =SUM(B11:F11) -> 21262911
A14: NPV (PV − Initial Investment) | B14: =B13+B3 -> -737089.29
A16: Cash flow series for IRR: | B16: =IRR(B3:F9) -> 0.041071741
A17: Year 0 (Initial invest.) | B17: =B3 -> -22000000
A18: Year 1 | B18: =B9 -> 922800
A19: Year 2 | B19: =C9 -> 1272996
A20: Year 3 | B20: =D9 -> 1327320
A21: Year 4 | B21: =E9 -> 1393236
A22: Year 5 (incl. terminal) | B22: =F9 -> 28060084
A24: Portfolio IRR: | B24: =IRR(B17:B22) -> 0.091808811
A26: NPV SENSITIVITY (Discount Rate vs Terminal Cap Rate)
A27: NPV (₹ lakh) ↓ Disc. Rate → Cap Rate | B27: 4.5% cap | C27: 5.0% cap | D27: 5.5% cap | E27: 6.0% cap | F27: 6.5% cap
A28: 8% disc. rate | B28: 15.7 | C28: -3.3 | D28: -18.9 | E28: -31.9 | F28: -42.9
A29: 9% disc. rate | B29: 5.9 | C29: -12.3 | D29: -27.2 | E29: -39.6 | F29: -50.1
A30: 10% disc. rate | B30: -3.4 | C30: -20.7 | D30: -35 | E30: -46.8 | F30: -56.9
A31: 11% disc. rate | B31: -12.2 | C31: -28.8 | D31: -42.4 | E31: -53.7 | F31: -63.3
A32: 12% disc. rate | B32: -20.5 | C32: -36.4 | D32: -49.4 | E32: -60.2 | F32: -69.4

Sheet Property Summary
A1: Rental Property - DASHBOARD
A2: Metric | B2: Sector 15 Apartment | C2: DLF Phase 2 Villa | D2: NIT 5 Commercial | E2: Sushant Lok Studio
A3: Monthly gross rent (₹) | B3: 42000 | C3: 55000 | D3: 14000 | E3: 18000
A4: Annual gross rent (₹) | B4: 504000 | C4: 660000 | D4: 168000 | E4: 144000
A5: Vacancy allowance (₹) | B5: -25200 | C5: -26400 | D5: -33600 | E5: -48000
A6: Net rental income (₹) | B6: 478800 | C6: 633600 | D6: 134400 | E6: 96000
A8: Property tax (₹) | B8: -24000 | C8: -48000 | D8: -18000 | E8: -12000
A9: Maintenance & repairs (₹) | B9: -36000 | C9: -60000 | D9: -24000 | E9: -60000
A10: Staff / management cost (₹) | B10: -60000 | C10: -66000 | D10: -60000 | E10: 0
A11: Total expenses (₹) | B11: -120000 | C11: -174000 | D11: -102000 | E11: -72000
A13: NET CASH FLOW (₹) | B13: 358800 | C13: 459600 | D13: 32400 | E13: 24000
A14: Net yield % (NCF ÷ portfolio cost) | B14: 0.0163 | C14: 0.0209 | D14: 0.0015 | E14: 0.0011
A15: Occupancy rate | B15: 1 | C15: 1 | D15: 0.5 | E15: 0.67
A16: # Active tenants | B16: 2 | C16: 1 | D16: 1 | E16: 0
A17: Status | B17: Fully Let | C17: Renew Soon | D17: Partially Let | E17: Vacant
